pyams_i18n_views/__init__.py
pyams_i18n_views/include.py
pyams_i18n_views/interfaces.py
pyams_i18n_views/doctests/README.rst
pyams_i18n_views/locales/pyams_i18n_views.pot
pyams_i18n_views/locales/fr/LC_MESSAGES/pyams_i18n_views.mo
pyams_i18n_views/locales/fr/LC_MESSAGES/pyams_i18n_views.po
pyams_i18n_views/skin/__init__.py
pyams_i18n_views/skin/resources/img/flags/aa.png
pyams_i18n_views/skin/resources/img/flags/aa_ET.png
pyams_i18n_views/skin/resources/img/flags/ab.png
pyams_i18n_views/skin/resources/img/flags/ab_GE.png
pyams_i18n_views/skin/resources/img/flags/ae.png
pyams_i18n_views/skin/resources/img/flags/ae_IR.png
pyams_i18n_views/skin/resources/img/flags/af.png
pyams_i18n_views/skin/resources/img/flags/af_ZA.png
pyams_i18n_views/skin/resources/img/flags/ak.png
pyams_i18n_views/skin/resources/img/flags/ak_GH.png
pyams_i18n_views/skin/resources/img/flags/am.png
pyams_i18n_views/skin/resources/img/flags/am_ET.png
pyams_i18n_views/skin/resources/img/flags/an.png
pyams_i18n_views/skin/resources/img/flags/an_ES.png
pyams_i18n_views/skin/resources/img/flags/ar.png
pyams_i18n_views/skin/resources/img/flags/ar_AE.png
pyams_i18n_views/skin/resources/img/flags/ar_BH.png
pyams_i18n_views/skin/resources/img/flags/ar_DZ.png
pyams_i18n_views/skin/resources/img/flags/ar_EG.png
pyams_i18n_views/skin/resources/img/flags/ar_IQ.png
pyams_i18n_views/skin/resources/img/flags/ar_JO.png
pyams_i18n_views/skin/resources/img/flags/ar_KW.png
pyams_i18n_views/skin/resources/img/flags/ar_LB.png
pyams_i18n_views/skin/resources/img/flags/ar_LY.png
pyams_i18n_views/skin/resources/img/flags/ar_MA.png
pyams_i18n_views/skin/resources/img/flags/ar_OM.png
pyams_i18n_views/skin/resources/img/flags/ar_QA.png
pyams_i18n_views/skin/resources/img/flags/ar_SA.png
pyams_i18n_views/skin/resources/img/flags/ar_SY.png
pyams_i18n_views/skin/resources/img/flags/ar_TN.png
pyams_i18n_views/skin/resources/img/flags/ar_YE.png
pyams_i18n_views/skin/resources/img/flags/arn.png
pyams_i18n_views-2.0.2.dist-info/LICENSE
pyams_i18n_views-2.0.2.dist-info/METADATA
pyams_i18n_views-2.0.2.dist-info/WHEEL
pyams_i18n_views-2.0.2.dist-info/entry_points.txt
pyams_i18n_views-2.0.2.dist-info/namespace_packages.txt
pyams_i18n_views-2.0.2.dist-info/top_level.txt
pyams_i18n_views-2.0.2.dist-info/RECORD
