Metadata-Version: 2.1
Name: pyams-i18n-views
Version: 2.0.2
Summary: Browser views for PyAMS_i18n package
Home-page: https://pyams.readthedocs.io
Author: Thierry Florac
Author-email: tflorac@ulthar.net
License: ZPL
Keywords: Pyramid PyAMS
Classifier: License :: OSI Approved :: Zope Public License
Classifier: Development Status :: 4 - Beta
Classifier: Programming Language :: Python
Classifier: Framework :: Pyramid
Classifier: Topic :: Software Development :: Libraries :: Python Modules
License-File: LICENSE
Requires-Dist: setuptools
Requires-Dist: fanstatic
Requires-Dist: pyams-form
Requires-Dist: pyams-i18n
Requires-Dist: pyams-layer
Requires-Dist: pyams-security
Requires-Dist: pyams-utils
Requires-Dist: pyramid>=2.0.0
Requires-Dist: zope.component
Requires-Dist: zope.interface
Requires-Dist: zope.schema
Provides-Extra: test
Requires-Dist: pyams-site; extra == "test"
Requires-Dist: pyams-skin; extra == "test"
Requires-Dist: pyams-zmi; extra == "test"
Requires-Dist: pyramid-zcml; extra == "test"
Requires-Dist: zope.exceptions; extra == "test"
